<Properties StartupConfiguration="{0DF03184-816F-47DF-AA1E-BA5B7B0D247B}|Default">
  <MonoDevelop.Ide.Workbench ActiveDocument="API/Startup.cs">
    <Files>
      <File FileName="API/Controllers/UsersController.cs" Line="38" Column="1" />
      <File FileName="API/Startup.cs" Line="38" Column="15" />
    </Files>
    <Pads>
      <Pad Id="ProjectPad">
        <State name="__root__">
          <Node name="DatingApp" expanded="True">
            <Node name="API" expanded="True">
              <Node name="Controllers" expanded="True" />
              <Node name="Startup.cs" selected="True" />
            </Node>
          </Node>
        </State>
      </Pad>
    </Pads>
  </MonoDevelop.Ide.Workbench>
  <MonoDevelop.Ide.ItemProperties.API PreferredExecutionTarget="/Applications/Google Chrome.app" />
  <MonoDevelop.Ide.DebuggingService.PinnedWatches />
  <MonoDevelop.Ide.Workspace ActiveConfiguration="Debug" />
  <MonoDevelop.Ide.DebuggingService.Breakpoints>
    <BreakpointStore />
  </MonoDevelop.Ide.DebuggingService.Breakpoints>
  <MultiItemStartupConfigurations />
</Properties>